miko/__init__.py
miko/__main__.py
miko/cmdline/__init__.py
miko/cmdline/base.py
miko/graph/__init__.py
miko/graph/plotting.py
miko/metad/__init__.py
miko/metad/fes.py
miko/metad/hills.py
miko/metad/profile.py
miko/metad/string.py
miko/structure/__init__.py
miko/structure/cluster.py
miko/tesla/__init__.py
miko/tesla/ai2_kit/__init__.py
miko/tesla/ai2_kit/exploration.py
miko/tesla/ai2_kit/labeling.py
miko/tesla/ai2_kit/task.py
miko/tesla/ai2_kit/training.py
miko/tesla/base/__init__.py
miko/tesla/base/exploration.py
miko/tesla/base/labeling.py
miko/tesla/base/task.py
miko/tesla/base/training.py
miko/tesla/dpgen/__init__.py
miko/tesla/dpgen/exploration.py
miko/tesla/dpgen/labeling.py
miko/tesla/dpgen/task.py
miko/tesla/dpgen/training.py
miko/utils/__init__.py
miko/utils/files.py
miko/utils/lammps.py
miko/utils/log_factory.py
miko/utils/output.py
miko_analyzer-0.3.3.dist-info/LICENSE
miko_analyzer-0.3.3.dist-info/WHEEL
miko_analyzer-0.3.3.dist-info/METADATA
miko_analyzer-0.3.3.dist-info/entry_points.txt
miko_analyzer-0.3.3.dist-info/RECORD
